CHANGES.txt
CONTRIBUTORS.txt
MANIFEST.in
README.txt
setup.cfg
setup.py
Products/__init__.py
Products.Person.egg-info/PKG-INFO
Products.Person.egg-info/SOURCES.txt
Products.Person.egg-info/dependency_links.txt
Products.Person.egg-info/entry_points.txt
Products.Person.egg-info/namespace_packages.txt
Products.Person.egg-info/not-zip-safe
Products.Person.egg-info/paster_plugins.txt
Products.Person.egg-info/requires.txt
Products.Person.egg-info/top_level.txt
Products/Person/README.txt
Products/Person/__init__.py
Products/Person/config.py
Products/Person/configure.zcml
Products/Person/interfaces.py
Products/Person/setuphandlers.py
Products/Person/tests.py
Products/Person/browser/__init__.py
Products/Person/browser/configure.zcml
Products/Person/browser/person.pt
Products/Person/content/__init__.py
Products/Person/content/configure.zcml
Products/Person/content/person.py
Products/Person/locales/Products.Person.pot
Products/Person/portlets/__init__.py
Products/Person/portlets/configure.zcml
Products/Person/profiles/default/browserlayer.xml
Products/Person/profiles/default/catalog.xml
Products/Person/profiles/default/diff_tool.xml
Products/Person/profiles/default/factorytool.xml
Products/Person/profiles/default/import_steps.xml
Products/Person/profiles/default/metadata.xml
Products/Person/profiles/default/portal_atct.xml
Products/Person/profiles/default/portlets.xml
Products/Person/profiles/default/rolemap.xml
Products/Person/profiles/default/tinymce.xml
Products/Person/profiles/default/types.xml
Products/Person/profiles/default/types/Person.xml
Products/Person/tests/__init__.py
Products/Person/tests/doc_tests.py
docs/HISTORY.txt
docs/INSTALL.txt
docs/LICENSE.GPL
docs/LICENSE.txt