Metadata-Version: 1.0
Name: Products.Person
Version: 0.1.6
Summary: A representation of a person.
Home-page: https://svn.v2.nl/plone/Products.Person
Author: Rui Guerra
Author-email: rui AT v2 DOT nl
License: GPL
Platform: UNKNOWN
Classifier: Framework :: Plone
Classifier: Intended Audience :: Developers
Classifier: Topic :: Software Development :: Libraries :: Python Modules
Classifier: License :: OSI Approved :: GNU General Public License (GPL)
